src/.gitattributes
src/__init__.py
src/cli.py
src/document_path.py
src/file_handler.py
src/model.py
src/obsidian.py
src/tag_set.py
src/utils.py
paperless_exporter-0.4.3.dist-info/METADATA
paperless_exporter-0.4.3.dist-info/WHEEL
paperless_exporter-0.4.3.dist-info/entry_points.txt
paperless_exporter-0.4.3.dist-info/licenses/LICENSE
paperless_exporter-0.4.3.dist-info/RECORD
