Metadata-Version: 2.4
Name: paperless-exporter
Version: 0.4.3
Summary: Paperless to Obsidian exporter
Author: Joscha Feth
Maintainer-email: Joscha Feth <joscha@feth.com>
License: MIT
License-File: LICENSE
Keywords: export,mariner,markdown,obsidian,paperless
Classifier: Development Status :: 3 - Alpha
Classifier: Intended Audience :: End Users/Desktop
Classifier: License :: OSI Approved :: MIT License
Classifier: Programming Language :: Python :: 3
Classifier: Programming Language :: Python :: 3.12
Classifier: Programming Language :: Python :: 3.13
Requires-Python: >=3.12
Requires-Dist: pathvalidate>=3.2.3
Requires-Dist: peewee>=3.17.9
Requires-Dist: python-frontmatter>=1.1.0
Requires-Dist: python-slugify>=8.0.4
Requires-Dist: tqdm>=4.67.1
